openfoundry/__init__.py
openfoundry/py.typed
openfoundry/cli/__init__.py
openfoundry/cli/main.py
openfoundry/communication/__init__.py
openfoundry/communication/http/__init__.py
openfoundry/communication/http/app.py
openfoundry/communication/http/state.py
openfoundry/communication/http/routes/__init__.py
openfoundry/communication/http/routes/agents.py
openfoundry/communication/http/routes/health.py
openfoundry/communication/http/routes/tasks.py
openfoundry/communication/http/routes/workflows.py
openfoundry/config/__init__.py
openfoundry/config/settings.py
openfoundry/conveyor/__init__.py
openfoundry/conveyor/agents/__init__.py
openfoundry/conveyor/agents/devops.py
openfoundry/conveyor/agents/release.py
openfoundry/core/__init__.py
openfoundry/core/agent_registry.py
openfoundry/core/base_agent.py
openfoundry/core/context.py
openfoundry/core/protocols.py
openfoundry/core/task.py
openfoundry/forge/__init__.py
openfoundry/forge/agents/__init__.py
openfoundry/forge/agents/architect.py
openfoundry/forge/agents/engineer.py
openfoundry/forge/agents/quality.py
openfoundry/llm/__init__.py
openfoundry/llm/provider.py
openfoundry/llm/router.py
openfoundry/orchestrator/__init__.py
openfoundry/orchestrator/coordinator.py
openfoundry/orchestrator/workflow_engine.py
openfoundry/shield/__init__.py
openfoundry/shield/guardrails/__init__.py
openfoundry/shield/guardrails/base.py
openfoundry/shield/guardrails/pii_detector.py
openfoundry/shield/guardrails/prompt_injection.py
openfoundry/watchtower/__init__.py
openfoundry/watchtower/telemetry/__init__.py
openfoundry/watchtower/telemetry/logging.py
openfoundry/watchtower/telemetry/metrics.py
openfoundry/watchtower/telemetry/setup.py
openfoundry-0.1.0.dist-info/METADATA
openfoundry-0.1.0.dist-info/WHEEL
openfoundry-0.1.0.dist-info/entry_points.txt
openfoundry-0.1.0.dist-info/top_level.txt
openfoundry-0.1.0.dist-info/RECORD
